README.rst
setup.py
unilog/__init__.py
unilog/compat.py
unilog/convert.py
unilog/unilog.py
unilog.egg-info/PKG-INFO
unilog.egg-info/SOURCES.txt
unilog.egg-info/dependency_links.txt
unilog.egg-info/not-zip-safe
unilog.egg-info/top_level.txt